[
    {
        "key": "dbln",
        "value": "%7B%2261580139921634%22%3A%22xkF4kzoI%22%7D",
        "domain": "facebook.com",
        "path": "/login/device-based/",
        "hostOnly": false,
        "creation": "2026-02-09T15:19:56.076Z",
        "lastAccessed": "2026-02-09T15:19:56.076Z"
    },
    {
        "key": "datr",
        "value": "iwWJaRfm9SPbP-DoXlyM335p",
        "domain": "facebook.com",
        "path": "/",
        "hostOnly": false,
        "creation": "2026-02-09T15:19:56.076Z",
        "lastAccessed": "2026-02-09T15:19:56.076Z"
    },
    {
        "key": "sb",
        "value": "iwWJaUoCuA52aJxnxEfMJ3hF",
        "domain": "facebook.com",
        "path": "/",
        "hostOnly": false,
        "creation": "2026-02-09T15:19:56.076Z",
        "lastAccessed": "2026-02-09T15:19:56.076Z"
    },
    {
        "key": "c_user",
        "value": "61580139921634",
        "domain": "facebook.com",
        "path": "/",
        "hostOnly": false,
        "creation": "2026-02-09T15:19:56.076Z",
        "lastAccessed": "2026-02-09T15:19:56.076Z"
    },
    {
        "key": "xs",
        "value": "7%3AQRmpmZTcPJzEZg%3A2%3A1770587628%3A-1%3A-1",
        "domain": "facebook.com",
        "path": "/",
        "hostOnly": false,
        "creation": "2026-02-09T15:19:56.076Z",
        "lastAccessed": "2026-02-09T15:19:56.076Z"
    },
    {
        "key": "locale",
        "value": "ar_AR",
        "domain": "facebook.com",
        "path": "/",
        "hostOnly": false,
        "creation": "2026-02-09T15:19:56.076Z",
        "lastAccessed": "2026-02-09T15:19:56.076Z"
    },
    {
        "key": "pas",
        "value": "61580139921634%3ADhpJhCbHkU",
        "domain": "facebook.com",
        "path": "/",
        "hostOnly": false,
        "creation": "2026-02-09T15:19:56.076Z",
        "lastAccessed": "2026-02-09T15:19:56.076Z"
    },
    {
        "key": "vpd",
        "value": "v1%3B778x393x2.75",
        "domain": "facebook.com",
        "path": "/",
        "hostOnly": false,
        "creation": "2026-02-09T15:19:56.076Z",
        "lastAccessed": "2026-02-09T15:19:56.076Z"
    },
    {
        "key": "fr",
        "value": "0rZH8pN0ttdC8M1Il.AWe0wYUg4KSahpuQdEKX6spUDufaRf9gVtljwoRHWDbMMgnXm4M.BpiQWL..AAA.0.0.BpifsT.AWeHlHdICdyx3aRyXW02sohm5E4",
        "domain": "facebook.com",
        "path": "/",
        "hostOnly": false,
        "creation": "2026-02-09T15:19:56.076Z",
        "lastAccessed": "2026-02-09T15:19:56.076Z"
    },
    {
        "key": "fbl_st",
        "value": "100731203%3BT%3A29510839",
        "domain": "facebook.com",
        "path": "/",
        "hostOnly": false,
        "creation": "2026-02-09T15:19:56.076Z",
        "lastAccessed": "2026-02-09T15:19:56.076Z"
    },
    {
        "key": "wl_cbv",
        "value": "v2%3Bclient_version%3A3080%3Btimestamp%3A1770650387",
        "domain": "facebook.com",
        "path": "/",
        "hostOnly": false,
        "creation": "2026-02-09T15:19:56.076Z",
        "lastAccessed": "2026-02-09T15:19:56.076Z"
    }
]
